{"CMT_projects":
[
   {
      "name": "Hydrotrend and Friends", 
      "components": [
         "Avulsion", 
         "CEM", 
         "Coastal", 
         "Hydrotrend", 
         "Waves"
      ], 
      "show": true
   }, 
   {
      "name": "Child and Sedflux", 
      "components": [
         "Baselevel", 
         "Child", 
         "Coastal", 
         "Sedflux2D", 
         "Sedflux3D"
      ], 
      "show": false
   }, 
   {
      "name": "Erode", 
      "components": [
         "D8Global", 
         "DEMSmoother", 
         "ErodeGlobal", 
         "ErodeLocal"
      ], 
      "show": false
   }, 
   {
      "name": "TopoFlow + GC2D", 
      "components": [
         "ChannelsDiffWave", 
         "ChannelsDynamWave", 
         "ChannelsKinWave", 
         "DataHIS", 
         "Diversions", 
         "EvapEnergyBalance", 
         "EvapPriestleyTaylor", 
         "EvapReadFile", 
         "IceGC2D", 
         "InfilGreenAmpt", 
         "InfilRichards1D", 
         "InfilSmithParlange", 
         "Meteorology", 
         "SatZoneDarcyLayers", 
         "SnowDegreeDay", 
         "SnowEnergyBalance", 
         "TestService", 
         "TopoFlow"
      ], 
      "show": false
   }
]
}